{"lmfTDQMRoOjXiP1Sw50ZxQ==":"pexels-spacex-60132-506x337.jpg","nZ3bOF1qxXoFC699LhoyTw==":"pexels-tom-d-arby-3904203-8398542-506x704.jpg","XHa6+nbunEs63XptAtOlzw==":"pexels-igor-starkov-233202-785529-506x298.jpg","FdAlJp+viazqOOCqHsQ0nA==":"pexels-life-of-pix-2489-506x337.jpg","tecvMM1t1I8zb8PJsy6EwQ==":"pexels-quang-nguyen-vinh-222549-10615217-506x337.jpg","QyjkL1M1Q3QkcckioTrLAA==":"pexels-pixabay-256381-506x337.jpg","e4dmYDik6//t/oEakbYvmQ==":"79577302-121x21.png","+hDPLPKYfOkbtl96osMtuQ==":"screenshot%202024-08-07%20at%2000.27.57-700x616.png","xV9irGfpM9aBZZZAEkFG4g==":"pexels-piotr-arnoldes-7862031-6109677-696x462.jpg","TqfTdSijYEBkKlBxUxf/Zg==":"unicef-640x375.jpg","wanXjWzLyjyvwHOjLr1Anw==":"pexels-matreding-7108779-696x1044.jpg","JPgUP018UJ0O0jNBMorbBA==":"letter-m-138x138.png"}